Workbook

Sheet README
B2: Hotel Revenue & Demand Analysis
B3: A synthetic revenue-management workbook covering KPI reporting, demand patterns, segment mix, competitive positioning, booking pace, group displacement and forward forecasting for a city-centre hotel.
B5: Data | C5: Fully synthetic - one year (Jan-Dec 2025) of daily bookings for a fictional 300-room city-centre hotel ("Meridian City Hotel"). No real property, guest or transaction data is used anywhere in this workbook.
B6: Currency | C6: All figures in GBP (£).
B7: Structure | C7: Raw_Data (segment-level daily bookings) -> Daily_Totals (one row per date) -> KPI_Summary / Weekly_Summary / Segment_Analysis / Demand_Pattern (formula-driven from the tables above). Pickup_Detail (lead-time bookings) -> Pickup_Report (pace curves). Group_Displacement and Forecast are standalone analysis tabs.
B8: Comp Set | C8: The three competitor rows on the CompSet tab are illustrative estimates for demonstration purposes only, marked in blue - not real competitor data.
B9: Forecast assumptions | C9: The Forecast tab applies simple YoY growth assumptions (blue, editable cells) to prior-year monthly figures. A production forecast would weight recent pickup pace (see Pickup_Report) more heavily than a flat growth rate - noted on that tab.
B10: Formulas | C10: Every summary figure is a live formula (SUMIFS / AVERAGEIF / INDEX-MATCH) referencing source data - nothing is hardcoded except the clearly-marked blue assumption cells. Change any input and the workbook recalculates.
B11: Purpose | C11: Built as a portfolio piece to demonstrate the analysis a Revenue Analyst role requires: occupancy/ADR/RevPAR reporting at daily/weekly/monthly cadence, demand and pace/pickup analysis, segment/channel mix, comp-set positioning (MPI/ARI/RGI), group displacement evaluation, and revenue forecasting.
B13: Tabs
C14: - Raw_Data
C15: - Daily_Totals
C16: - KPI_Summary
C17: - Weekly_Summary
C18: - Segment_Analysis
C19: - Demand_Pattern
C20: - CompSet
C21: - Pickup_Detail
C22: - Pickup_Report
C23: - Group_Displacement
C24: - Forecast
C25: - Dashboard
C26: - Recommendations

Sheet Raw_Data
A1: Date | B1: DayOfWeek | C1: MonthName | D1: MonthNum | E1: WeekNum | F1: Segment | G1: Channel | H1: RoomsSold | I1: RoomRevenue | J1: RoomsAvailable
A2: 2025-01-01 | B2: Wednesday | C2: January | D2: 1 | E2: 1 | F2: Corporate | G2: Direct/Negotiated | H2: 71 | I2: 7528.84 | J2: 300
A3: 2025-01-01 | B3: Wednesday | C3: January | D3: 1 | E3: 1 | F3: Leisure | G3: Direct/Website | H3: 15 | I3: 1542.75 | J3: 300
A4: 2025-01-01 | B4: Wednesday | C4: January | D4: 1 | E4: 1 | F4: Group | G4: Direct/MICE | H4: 20 | I4: 1715.4 | J4: 300
A5: 2025-01-01 | B5: Wednesday | C5: January | D5: 1 | E5: 1 | F5: OTA | G5: OTA | H5: 25 | I5: 2109 | J5: 300
A6: 2025-01-02 | B6: Thursday | C6: January | D6: 1 | E6: 1 | F6: Corporate | G6: Direct/Negotiated | H6: 66 | I6: 7287.06 | J6: 300
A7: 2025-01-02 | B7: Thursday | C7: January | D7: 1 | E7: 1 | F7: Leisure | G7: Direct/Website | H7: 14 | I7: 1282.54 | J7: 300
A8: 2025-01-02 | B8: Thursday | C8: January | D8: 1 | E8: 1 | F8: Group | G8: Direct/MICE | H8: 21 | I8: 1617 | J8: 300
A9: 2025-01-02 | B9: Thursday | C9: January | D9: 1 | E9: 1 | F9: OTA | G9: OTA | H9: 18 | I9: 1402.74 | J9: 300
A10: 2025-01-03 | B10: Friday | C10: January | D10: 1 | E10: 1 | F10: Corporate | G10: Direct/Negotiated | H10: 62 | I10: 6754.28 | J10: 300
A11: 2025-01-03 | B11: Friday | C11: January | D11: 1 | E11: 1 | F11: Leisure | G11: Direct/Website | H11: 13 | I11: 1121.25 | J11: 300
A12: 2025-01-03 | B12: Friday | C12: January | D12: 1 | E12: 1 | F12: Group | G12: Direct/MICE | H12: 23 | I12: 1973.63 | J12: 300
A13: 2025-01-03 | B13: Friday | C13: January | D13: 1 | E13: 1 | F13: OTA | G13: OTA | H13: 22 | I13: 1622.5 | J13: 300
... A1461: 2025-12-31 | B1461: Wednesday | C1461: December | D1461: 12 | E1461: 53 | F1461: OTA | G1461: OTA | H1461: 27 | I1461: 2492.37 | J1461: 300

Sheet Daily_Totals
A1: Date | B1: DayOfWeek | C1: MonthName | D1: MonthNum | E1: WeekNum | F1: RoomsSold | G1: RoomRevenue | H1: RoomsAvailable | I1: Occupancy | J1: ADR | K1: RevPAR
A2: 2025-01-01 | B2: Wednesday | C2: January | D2: 1 | E2: 1 | F2: =SUMIFS(Raw_Data!$H$2:$H$1461,Raw_Data!$A$2:$A$1461,A2) -> 131 | G2: =SUMIFS(Raw_Data!$I$2:$I$1461,Raw_Data!$A$2:$A$1461,A2) -> 12895.99 | H2: 300 | I2: =F2/H2 -> 0.43666667 | J2: =IFERROR(G2/F2,0) -> 98.442672 | K2: =G2/H2 -> 42.986633
A3: 2025-01-02 | B3: Thursday | C3: January | D3: 1 | E3: 1 | F3: =SUMIFS(Raw_Data!$H$2:$H$1461,Raw_Data!$A$2:$A$1461,A3) -> 119 | G3: =SUMIFS(Raw_Data!$I$2:$I$1461,Raw_Data!$A$2:$A$1461,A3) -> 11589.34 | H3: 300 | I3: =F3/H3 -> 0.39666667 | J3: =IFERROR(G3/F3,0) -> 97.389412 | K3: =G3/H3 -> 38.631133
A4: 2025-01-03 | B4: Friday | C4: January | D4: 1 | E4: 1 | F4: =SUMIFS(Raw_Data!$H$2:$H$1461,Raw_Data!$A$2:$A$1461,A4) -> 120 | G4: =SUMIFS(Raw_Data!$I$2:$I$1461,Raw_Data!$A$2:$A$1461,A4) -> 11471.66 | H4: 300 | I4: =F4/H4 -> 0.4 | J4: =IFERROR(G4/F4,0) -> 95.597167 | K4: =G4/H4 -> 38.238867
A5: 2025-01-04 | B5: Saturday | C5: January | D5: 1 | E5: 1 | F5: =SUMIFS(Raw_Data!$H$2:$H$1461,Raw_Data!$A$2:$A$1461,A5) -> 83 | G5: =SUMIFS(Raw_Data!$I$2:$I$1461,Raw_Data!$A$2:$A$1461,A5) -> 7848.84 | H5: 300 | I5: =F5/H5 -> 0.27666667 | J5: =IFERROR(G5/F5,0) -> 94.564337 | K5: =G5/H5 -> 26.1628
A6: 2025-01-05 | B6: Sunday | C6: January | D6: 1 | E6: 1 | F6: =SUMIFS(Raw_Data!$H$2:$H$1461,Raw_Data!$A$2:$A$1461,A6) -> 91 | G6: =SUMIFS(Raw_Data!$I$2:$I$1461,Raw_Data!$A$2:$A$1461,A6) -> 7860.2 | H6: 300 | I6: =F6/H6 -> 0.30333333 | J6: =IFERROR(G6/F6,0) -> 86.375824 | K6: =G6/H6 -> 26.200667
A7: 2025-01-06 | B7: Monday | C7: January | D7: 1 | E7: 2 | F7: =SUMIFS(Raw_Data!$H$2:$H$1461,Raw_Data!$A$2:$A$1461,A7) -> 125 | G7: =SUMIFS(Raw_Data!$I$2:$I$1461,Raw_Data!$A$2:$A$1461,A7) -> 12397.62 | H7: 300 | I7: =F7/H7 -> 0.41666667 | J7: =IFERROR(G7/F7,0) -> 99.18096 | K7: =G7/H7 -> 41.3254
A8: 2025-01-07 | B8: Tuesday | C8: January | D8: 1 | E8: 2 | F8: =SUMIFS(Raw_Data!$H$2:$H$1461,Raw_Data!$A$2:$A$1461,A8) -> 129 | G8: =SUMIFS(Raw_Data!$I$2:$I$1461,Raw_Data!$A$2:$A$1461,A8) -> 11926.23 | H8: 300 | I8: =F8/H8 -> 0.43 | J8: =IFERROR(G8/F8,0) -> 92.451395 | K8: =G8/H8 -> 39.7541
A9: 2025-01-08 | B9: Wednesday | C9: January | D9: 1 | E9: 2 | F9: =SUMIFS(Raw_Data!$H$2:$H$1461,Raw_Data!$A$2:$A$1461,A9) -> 116 | G9: =SUMIFS(Raw_Data!$I$2:$I$1461,Raw_Data!$A$2:$A$1461,A9) -> 11164.34 | H9: 300 | I9: =F9/H9 -> 0.38666667 | J9: =IFERROR(G9/F9,0) -> 96.24431 | K9: =G9/H9 -> 37.214467
A10: 2025-01-09 | B10: Thursday | C10: January | D10: 1 | E10: 2 | F10: =SUMIFS(Raw_Data!$H$2:$H$1461,Raw_Data!$A$2:$A$1461,A10) -> 130 | G10: =SUMIFS(Raw_Data!$I$2:$I$1461,Raw_Data!$A$2:$A$1461,A10) -> 13533.73 | H10: 300 | I10: =F10/H10 -> 0.43333333 | J10: =IFERROR(G10/F10,0) -> 104.10562 | K10: =G10/H10 -> 45.112433
A11: 2025-01-10 | B11: Friday | C11: January | D11: 1 | E11: 2 | F11: =SUMIFS(Raw_Data!$H$2:$H$1461,Raw_Data!$A$2:$A$1461,A11) -> 121 | G11: =SUMIFS(Raw_Data!$I$2:$I$1461,Raw_Data!$A$2:$A$1461,A11) -> 12312.33 | H11: 300 | I11: =F11/H11 -> 0.40333333 | J11: =IFERROR(G11/F11,0) -> 101.75479 | K11: =G11/H11 -> 41.0411
A12: 2025-01-11 | B12: Saturday | C12: January | D12: 1 | E12: 2 | F12: =SUMIFS(Raw_Data!$H$2:$H$1461,Raw_Data!$A$2:$A$1461,A12) -> 98 | G12: =SUMIFS(Raw_Data!$I$2:$I$1461,Raw_Data!$A$2:$A$1461,A12) -> 8839.71 | H12: 300 | I12: =F12/H12 -> 0.32666667 | J12: =IFERROR(G12/F12,0) -> 90.201122 | K12: =G12/H12 -> 29.4657
A13: 2025-01-12 | B13: Sunday | C13: January | D13: 1 | E13: 2 | F13: =SUMIFS(Raw_Data!$H$2:$H$1461,Raw_Data!$A$2:$A$1461,A13) -> 88 | G13: =SUMIFS(Raw_Data!$I$2:$I$1461,Raw_Data!$A$2:$A$1461,A13) -> 8077.06 | H13: 300 | I13: =F13/H13 -> 0.29333333 | J13: =IFERROR(G13/F13,0) -> 91.784773 | K13: =G13/H13 -> 26.923533
... A366: 2025-12-31 | B366: Wednesday | C366: December | D366: 12 | E366: 53 | F366: =SUMIFS(Raw_Data!$H$2:$H$1461,Raw_Data!$A$2:$A$1461,A366) -> 148 | G366: =SUMIFS(Raw_Data!$I$2:$I$1461,Raw_Data!$A$2:$A$1461,A366) -> 16171.3 | H366: 300 | I366: =F366/H366 -> 0.49333333 | J366: =IFERROR(G366/F366,0) -> 109.26554 | K366: =G366/H366 -> 53.904333

Sheet KPI_Summary
A1: Monthly Revenue-Management KPIs
A3: Month | B3: RoomNightsSold | C3: RoomNightsAvailable | D3: RoomRevenue | E3: Occupancy % | F3: ADR | G3: RevPAR
A4: January | B4: =SUMIFS(Daily_Totals!$F$2:$F$366,Daily_Totals!$C$2:$C$366,A4) -> 3558 | C4: =300*31 -> 9300 | D4: =SUMIFS(Daily_Totals!$G$2:$G$366,Daily_Totals!$C$2:$C$366,A4) -> 347019.29 | E4: =B4/C4 -> 0.38258065 | F4: =IFERROR(D4/B4,0) -> 97.532122 | G4: =D4/C4 -> 37.313902
A5: February | B5: =SUMIFS(Daily_Totals!$F$2:$F$366,Daily_Totals!$C$2:$C$366,A5) -> 3801 | C5: =300*28 -> 8400 | D5: =SUMIFS(Daily_Totals!$G$2:$G$366,Daily_Totals!$C$2:$C$366,A5) -> 384120.68 | E5: =B5/C5 -> 0.4525 | F5: =IFERROR(D5/B5,0) -> 101.0578 | G5: =D5/C5 -> 45.728652
A6: March | B6: =SUMIFS(Daily_Totals!$F$2:$F$366,Daily_Totals!$C$2:$C$366,A6) -> 4957 | C6: =300*31 -> 9300 | D6: =SUMIFS(Daily_Totals!$G$2:$G$366,Daily_Totals!$C$2:$C$366,A6) -> 528388.89 | E6: =B6/C6 -> 0.53301075 | F6: =IFERROR(D6/B6,0) -> 106.59449 | G6: =D6/C6 -> 56.81601
A7: April | B7: =SUMIFS(Daily_Totals!$F$2:$F$366,Daily_Totals!$C$2:$C$366,A7) -> 4864 | C7: =300*30 -> 9000 | D7: =SUMIFS(Daily_Totals!$G$2:$G$366,Daily_Totals!$C$2:$C$366,A7) -> 521261.47 | E7: =B7/C7 -> 0.54044444 | F7: =IFERROR(D7/B7,0) -> 107.16724 | G7: =D7/C7 -> 57.917941
A8: May | B8: =SUMIFS(Daily_Totals!$F$2:$F$366,Daily_Totals!$C$2:$C$366,A8) -> 5284 | C8: =300*31 -> 9300 | D8: =SUMIFS(Daily_Totals!$G$2:$G$366,Daily_Totals!$C$2:$C$366,A8) -> 570703.13 | E8: =B8/C8 -> 0.56817204 | F8: =IFERROR(D8/B8,0) -> 108.00589 | G8: =D8/C8 -> 61.365928
A9: June | B9: =SUMIFS(Daily_Totals!$F$2:$F$366,Daily_Totals!$C$2:$C$366,A9) -> 5158 | C9: =300*30 -> 9000 | D9: =SUMIFS(Daily_Totals!$G$2:$G$366,Daily_Totals!$C$2:$C$366,A9) -> 561176.74 | E9: =B9/C9 -> 0.57311111 | F9: =IFERROR(D9/B9,0) -> 108.79735 | G9: =D9/C9 -> 62.352971
A10: July | B10: =SUMIFS(Daily_Totals!$F$2:$F$366,Daily_Totals!$C$2:$C$366,A10) -> 4761 | C10: =300*31 -> 9300 | D10: =SUMIFS(Daily_Totals!$G$2:$G$366,Daily_Totals!$C$2:$C$366,A10) -> 500981.51 | E10: =B10/C10 -> 0.51193548 | F10: =IFERROR(D10/B10,0) -> 105.22611 | G10: =D10/C10 -> 53.86898
A11: August | B11: =SUMIFS(Daily_Totals!$F$2:$F$366,Daily_Totals!$C$2:$C$366,A11) -> 3315 | C11: =300*31 -> 9300 | D11: =SUMIFS(Daily_Totals!$G$2:$G$366,Daily_Totals!$C$2:$C$366,A11) -> 313208.13 | E11: =B11/C11 -> 0.35645161 | F11: =IFERROR(D11/B11,0) -> 94.48209 | G11: =D11/C11 -> 33.678294
A12: September | B12: =SUMIFS(Daily_Totals!$F$2:$F$366,Daily_Totals!$C$2:$C$366,A12) -> 5255 | C12: =300*30 -> 9000 | D12: =SUMIFS(Daily_Totals!$G$2:$G$366,Daily_Totals!$C$2:$C$366,A12) -> 581383.61 | E12: =B12/C12 -> 0.58388889 | F12: =IFERROR(D12/B12,0) -> 110.63437 | G12: =D12/C12 -> 64.598179
A13: October | B13: =SUMIFS(Daily_Totals!$F$2:$F$366,Daily_Totals!$C$2:$C$366,A13) -> 5523 | C13: =300*31 -> 9300 | D13: =SUMIFS(Daily_Totals!$G$2:$G$366,Daily_Totals!$C$2:$C$366,A13) -> 613019.31 | E13: =B13/C13 -> 0.59387097 | F13: =IFERROR(D13/B13,0) -> 110.9939 | G13: =D13/C13 -> 65.916055
A14: November | B14: =SUMIFS(Daily_Totals!$F$2:$F$366,Daily_Totals!$C$2:$C$366,A14) -> 4998 | C14: =300*30 -> 9000 | D14: =SUMIFS(Daily_Totals!$G$2:$G$366,Daily_Totals!$C$2:$C$366,A14) -> 539340.21 | E14: =B14/C14 -> 0.55533333 | F14: =IFERROR(D14/B14,0) -> 107.91121 | G14: =D14/C14 -> 59.92669
A15: December | B15: =SUMIFS(Daily_Totals!$F$2:$F$366,Daily_Totals!$C$2:$C$366,A15) -> 4359 | C15: =300*31 -> 9300 | D15: =SUMIFS(Daily_Totals!$G$2:$G$366,Daily_Totals!$C$2:$C$366,A15) -> 444263.06 | E15: =B15/C15 -> 0.46870968 | F15: =IFERROR(D15/B15,0) -> 101.91857 | G15: =D15/C15 -> 47.770222
A16: ANNUAL TOTAL | B16: =SUM(B4:B15) -> 55833 | C16: =SUM(C4:C15) -> 109500 | D16: =SUM(D4:D15) -> 5904866 | E16: =B16/C16 -> 0.50989041 | F16: =D16/B16 -> 105.75943 | G16: =D16/C16 -> 53.925717

Sheet Weekly_Summary
A1: Weekly Revenue-Management KPIs
A3: Week # | B3: Days in Week | C3: RoomNightsSold | D3: RoomRevenue | E3: Occupancy % | F3: ADR | G3: RevPAR
A4: 1 | B4: =COUNTIF(Daily_Totals!$E$2:$E$366,A4) -> 5 | C4: =SUMIFS(Daily_Totals!$F$2:$F$366,Daily_Totals!$E$2:$E$366,A4) -> 544 | D4: =SUMIFS(Daily_Totals!$G$2:$G$366,Daily_Totals!$E$2:$E$366,A4) -> 51666.03 | E4: =IFERROR(C4/(B4*300),0) -> 0.36266667 | F4: =IFERROR(D4/C4,0) -> 94.97432 | G4: =IFERROR(D4/(B4*300),0) -> 34.44402
A5: 2 | B5: =COUNTIF(Daily_Totals!$E$2:$E$366,A5) -> 7 | C5: =SUMIFS(Daily_Totals!$F$2:$F$366,Daily_Totals!$E$2:$E$366,A5) -> 807 | D5: =SUMIFS(Daily_Totals!$G$2:$G$366,Daily_Totals!$E$2:$E$366,A5) -> 78251.02 | E5: =IFERROR(C5/(B5*300),0) -> 0.38428571 | F5: =IFERROR(D5/C5,0) -> 96.965328 | G5: =IFERROR(D5/(B5*300),0) -> 37.26239
A6: 3 | B6: =COUNTIF(Daily_Totals!$E$2:$E$366,A6) -> 7 | C6: =SUMIFS(Daily_Totals!$F$2:$F$366,Daily_Totals!$E$2:$E$366,A6) -> 797 | D6: =SUMIFS(Daily_Totals!$G$2:$G$366,Daily_Totals!$E$2:$E$366,A6) -> 77370.3 | E6: =IFERROR(C6/(B6*300),0) -> 0.37952381 | F6: =IFERROR(D6/C6,0) -> 97.076913 | G6: =IFERROR(D6/(B6*300),0) -> 36.843
A7: 4 | B7: =COUNTIF(Daily_Totals!$E$2:$E$366,A7) -> 7 | C7: =SUMIFS(Daily_Totals!$F$2:$F$366,Daily_Totals!$E$2:$E$366,A7) -> 797 | D7: =SUMIFS(Daily_Totals!$G$2:$G$366,Daily_Totals!$E$2:$E$366,A7) -> 78091.06 | E7: =IFERROR(C7/(B7*300),0) -> 0.37952381 | F7: =IFERROR(D7/C7,0) -> 97.981255 | G7: =IFERROR(D7/(B7*300),0) -> 37.186219
A8: 5 | B8: =COUNTIF(Daily_Totals!$E$2:$E$366,A8) -> 7 | C8: =SUMIFS(Daily_Totals!$F$2:$F$366,Daily_Totals!$E$2:$E$366,A8) -> 816 | D8: =SUMIFS(Daily_Totals!$G$2:$G$366,Daily_Totals!$E$2:$E$366,A8) -> 81590.04 | E8: =IFERROR(C8/(B8*300),0) -> 0.38857143 | F8: =IFERROR(D8/C8,0) -> 99.987794 | G8: =IFERROR(D8/(B8*300),0) -> 38.8524
A9: 6 | B9: =COUNTIF(Daily_Totals!$E$2:$E$366,A9) -> 7 | C9: =SUMIFS(Daily_Totals!$F$2:$F$366,Daily_Totals!$E$2:$E$366,A9) -> 988 | D9: =SUMIFS(Daily_Totals!$G$2:$G$366,Daily_Totals!$E$2:$E$366,A9) -> 98748.02 | E9: =IFERROR(C9/(B9*300),0) -> 0.47047619 | F9: =IFERROR(D9/C9,0) -> 99.947389 | G9: =IFERROR(D9/(B9*300),0) -> 47.022867
A10: 7 | B10: =COUNTIF(Daily_Totals!$E$2:$E$366,A10) -> 7 | C10: =SUMIFS(Daily_Totals!$F$2:$F$366,Daily_Totals!$E$2:$E$366,A10) -> 960 | D10: =SUMIFS(Daily_Totals!$G$2:$G$366,Daily_Totals!$E$2:$E$366,A10) -> 97318.35 | E10: =IFERROR(C10/(B10*300),0) -> 0.45714286 | F10: =IFERROR(D10/C10,0) -> 101.37328 | G10: =IFERROR(D10/(B10*300),0) -> 46.342071
A11: 8 | B11: =COUNTIF(Daily_Totals!$E$2:$E$366,A11) -> 7 | C11: =SUMIFS(Daily_Totals!$F$2:$F$366,Daily_Totals!$E$2:$E$366,A11) -> 924 | D11: =SUMIFS(Daily_Totals!$G$2:$G$366,Daily_Totals!$E$2:$E$366,A11) -> 94939.63 | E11: =IFERROR(C11/(B11*300),0) -> 0.44 | F11: =IFERROR(D11/C11,0) -> 102.74852 | G11: =IFERROR(D11/(B11*300),0) -> 45.209348
A12: 9 | B12: =COUNTIF(Daily_Totals!$E$2:$E$366,A12) -> 7 | C12: =SUMIFS(Daily_Totals!$F$2:$F$366,Daily_Totals!$E$2:$E$366,A12) -> 989 | D12: =SUMIFS(Daily_Totals!$G$2:$G$366,Daily_Totals!$E$2:$E$366,A12) -> 99599.14 | E12: =IFERROR(C12/(B12*300),0) -> 0.47095238 | F12: =IFERROR(D12/C12,0) -> 100.70692 | G12: =IFERROR(D12/(B12*300),0) -> 47.428162
A13: 10 | B13: =COUNTIF(Daily_Totals!$E$2:$E$366,A13) -> 7 | C13: =SUMIFS(Daily_Totals!$F$2:$F$366,Daily_Totals!$E$2:$E$366,A13) -> 1124 | D13: =SUMIFS(Daily_Totals!$G$2:$G$366,Daily_Totals!$E$2:$E$366,A13) -> 118912.02 | E13: =IFERROR(C13/(B13*300),0) -> 0.5352381 | F13: =IFERROR(D13/C13,0) -> 105.79361 | G13: =IFERROR(D13/(B13*300),0) -> 56.624771
A14: 11 | B14: =COUNTIF(Daily_Totals!$E$2:$E$366,A14) -> 7 | C14: =SUMIFS(Daily_Totals!$F$2:$F$366,Daily_Totals!$E$2:$E$366,A14) -> 1123 | D14: =SUMIFS(Daily_Totals!$G$2:$G$366,Daily_Totals!$E$2:$E$366,A14) -> 120229.47 | E14: =IFERROR(C14/(B14*300),0) -> 0.5347619 | F14: =IFERROR(D14/C14,0) -> 107.06097 | G14: =IFERROR(D14/(B14*300),0) -> 57.252129
A15: 12 | B15: =COUNTIF(Daily_Totals!$E$2:$E$366,A15) -> 7 | C15: =SUMIFS(Daily_Totals!$F$2:$F$366,Daily_Totals!$E$2:$E$366,A15) -> 1156 | D15: =SUMIFS(Daily_Totals!$G$2:$G$366,Daily_Totals!$E$2:$E$366,A15) -> 124096.18 | E15: =IFERROR(C15/(B15*300),0) -> 0.55047619 | F15: =IFERROR(D15/C15,0) -> 107.34964 | G15: =IFERROR(D15/(B15*300),0) -> 59.093419
... A56: 53 | B56: =COUNTIF(Daily_Totals!$E$2:$E$366,A56) -> 3 | C56: =SUMIFS(Daily_Totals!$F$2:$F$366,Daily_Totals!$E$2:$E$366,A56) -> 421 | D56: =SUMIFS(Daily_Totals!$G$2:$G$366,Daily_Totals!$E$2:$E$366,A56) -> 45559.88 | E56: =IFERROR(C56/(B56*300),0) -> 0.46777778 | F56: =IFERROR(D56/C56,0) -> 108.21824 | G56: =IFERROR(D56/(B56*300),0) -> 50.622089

Sheet Segment_Analysis
A1: Segment & Channel Mix
A3: Segment | B3: Channel | C3: RoomNights | D3: Revenue | E3: ADR | F3: % of Revenue | G3: % of RoomNights
A4: Corporate | B4: Direct/Negotiated | C4: =SUMIFS(Raw_Data!$H$2:$H$1461,Raw_Data!$F$2:$F$1461,A4) -> 25497 | D4: =SUMIFS(Raw_Data!$I$2:$I$1461,Raw_Data!$F$2:$F$1461,A4) -> 3007128 | E4: =D4/C4 -> 117.94046 | F4: =D4/SUM($D$4:$D$7) -> 0.50926269 | G4: =C4/SUM($C$4:$C$7) -> 0.45666541
A5: Leisure | B5: Direct/Website | C5: =SUMIFS(Raw_Data!$H$2:$H$1461,Raw_Data!$F$2:$F$1461,A5) -> 10487 | D5: =SUMIFS(Raw_Data!$I$2:$I$1461,Raw_Data!$F$2:$F$1461,A5) -> 1084879.6 | E5: =D5/C5 -> 103.44995 | F5: =D5/SUM($D$4:$D$7) -> 0.18372637 | G5: =C5/SUM($C$4:$C$7) -> 0.18782799
A6: Group | B6: Direct/MICE | C6: =SUMIFS(Raw_Data!$H$2:$H$1461,Raw_Data!$F$2:$F$1461,A6) -> 8531 | D6: =SUMIFS(Raw_Data!$I$2:$I$1461,Raw_Data!$F$2:$F$1461,A6) -> 813459.17 | E6: =D6/C6 -> 95.35332 | F6: =D6/SUM($D$4:$D$7) -> 0.13776082 | G6: =C6/SUM($C$4:$C$7) -> 0.15279494
A7: OTA | B7: OTA | C7: =SUMIFS(Raw_Data!$H$2:$H$1461,Raw_Data!$F$2:$F$1461,A7) -> 11318 | D7: =SUMIFS(Raw_Data!$I$2:$I$1461,Raw_Data!$F$2:$F$1461,A7) -> 999399.3 | E7: =D7/C7 -> 88.301758 | F7: =D7/SUM($D$4:$D$7) -> 0.16925012 | G7: =C7/SUM($C$4:$C$7) -> 0.20271166
A8: TOTAL | C8: =SUM(C4:C7) -> 55833 | D8: =SUM(D4:D7) -> 5904866 | F8: =SUM(F4:F7) -> 1 | G8: =SUM(G4:G7) -> 1

Sheet Demand_Pattern
A1: Demand Pattern by Day of Week
A3: Day of Week | B3: Avg Occupancy % | C3: Avg ADR | D3: Avg RevPAR
A4: Monday | B4: =AVERAGEIF(Daily_Totals!$B$2:$B$366,A4,Daily_Totals!$I$2:$I$366) -> 0.55173077 | C4: =AVERAGEIF(Daily_Totals!$B$2:$B$366,A4,Daily_Totals!$J$2:$J$366) -> 106.98505 | D4: =AVERAGEIF(Daily_Totals!$B$2:$B$366,A4,Daily_Totals!$K$2:$K$366) -> 59.384323
A5: Tuesday | B5: =AVERAGEIF(Daily_Totals!$B$2:$B$366,A5,Daily_Totals!$I$2:$I$366) -> 0.55660256 | C5: =AVERAGEIF(Daily_Totals!$B$2:$B$366,A5,Daily_Totals!$J$2:$J$366) -> 106.2553 | D5: =AVERAGEIF(Daily_Totals!$B$2:$B$366,A5,Daily_Totals!$K$2:$K$366) -> 59.578033
A6: Wednesday | B6: =AVERAGEIF(Daily_Totals!$B$2:$B$366,A6,Daily_Totals!$I$2:$I$366) -> 0.55106918 | C6: =AVERAGEIF(Daily_Totals!$B$2:$B$366,A6,Daily_Totals!$J$2:$J$366) -> 107.41384 | D6: =AVERAGEIF(Daily_Totals!$B$2:$B$366,A6,Daily_Totals!$K$2:$K$366) -> 59.612294
A7: Thursday | B7: =AVERAGEIF(Daily_Totals!$B$2:$B$366,A7,Daily_Totals!$I$2:$I$366) -> 0.55423077 | C7: =AVERAGEIF(Daily_Totals!$B$2:$B$366,A7,Daily_Totals!$J$2:$J$366) -> 106.48524 | D7: =AVERAGEIF(Daily_Totals!$B$2:$B$366,A7,Daily_Totals!$K$2:$K$366) -> 59.435913
A8: Friday | B8: =AVERAGEIF(Daily_Totals!$B$2:$B$366,A8,Daily_Totals!$I$2:$I$366) -> 0.54955128 | C8: =AVERAGEIF(Daily_Totals!$B$2:$B$366,A8,Daily_Totals!$J$2:$J$366) -> 106.40112 | D8: =AVERAGEIF(Daily_Totals!$B$2:$B$366,A8,Daily_Totals!$K$2:$K$366) -> 58.98479
A9: Saturday | B9: =AVERAGEIF(Daily_Totals!$B$2:$B$366,A9,Daily_Totals!$I$2:$I$366) -> 0.39967949 | C9: =AVERAGEIF(Daily_Totals!$B$2:$B$366,A9,Daily_Totals!$J$2:$J$366) -> 98.434965 | D9: =AVERAGEIF(Daily_Totals!$B$2:$B$366,A9,Daily_Totals!$K$2:$K$366) -> 39.591571
A10: Sunday | B10: =AVERAGEIF(Daily_Totals!$B$2:$B$366,A10,Daily_Totals!$I$2:$I$366) -> 0.40557692 | C10: =AVERAGEIF(Daily_Totals!$B$2:$B$366,A10,Daily_Totals!$J$2:$J$366) -> 99.895963 | D10: =AVERAGEIF(Daily_Totals!$B$2:$B$366,A10,Daily_Totals!$K$2:$K$366) -> 40.783739

Sheet CompSet
A1: Competitive Set Positioning
A2: Competitor rows are illustrative estimates for demonstration only (shown in blue) - not real market data.
A4: Hotel | B4: Occupancy % | C4: ADR | D4: RevPAR
A5: Meridian City Hotel (Ours) | B5: =KPI_Summary!E16 -> 0.50989041 | C5: =KPI_Summary!F16 -> 105.75943 | D5: =KPI_Summary!G16 -> 53.925717
A6: Competitor A | B6: 0.552 | C6: 110 | D6: =B6*C6 -> 60.72
A7: Competitor B | B7: 0.478 | C7: 99 | D7: =B7*C7 -> 47.322
A8: Competitor C | B8: 0.531 | C8: 102 | D8: =B8*C8 -> 54.162
A9: Comp Set Average | B9: =AVERAGE(B6:B8) -> 0.52033333 | C9: =AVERAGE(C6:C8) -> 103.66667 | D9: =AVERAGE(D6:D8) -> 54.068
A11: Index vs. Comp Set | B11: Index
A12: MPI (Market Penetration Index) | B12: =B5/B9*100 -> 97.993032
A13: ARI (Average Rate Index) | B13: =C5/C9*100 -> 102.01874
A14: RGI (Revenue Generation Index) | B14: =D5/D9*100 -> 99.736845

Sheet Pickup_Detail
A1: StayMonth | B1: MonthNum | C1: Segment | D1: LeadDays | E1: RoomsBooked
A2: January | B2: 1 | C2: Corporate | D2: 0 | E2: 251
A3: January | B3: 1 | C3: Corporate | D3: 3 | E3: 418
A4: January | B4: 1 | C4: Corporate | D4: 7 | E4: 419
A5: January | B5: 1 | C5: Corporate | D5: 14 | E5: 330
A6: January | B6: 1 | C6: Corporate | D6: 21 | E6: 165
A7: January | B7: 1 | C7: Corporate | D7: 30 | E7: 84
A8: January | B8: 1 | C8: Group | D8: 30 | E8: 54
A9: January | B9: 1 | C9: Group | D9: 60 | E9: 111
A10: January | B10: 1 | C10: Group | D10: 90 | E10: 134
A11: January | B11: 1 | C11: Group | D11: 120 | E11: 137
A12: January | B12: 1 | C12: Group | D12: 180 | E12: 109
A13: January | B13: 1 | C13: Leisure | D13: 7 | E13: 32
... A265: December | B265: 12 | C265: OTA | D265: 21 | E265: 87

Sheet Pickup_Report
A1: Booking Pace / Pickup Report
A2: Cumulative room nights on the books at each lead-time checkpoint, as a % of total room nights available that month. October (strong season) vs December (soft season) — both post-summer months, useful pace comparison.
A4: Days Before Arrival | B4: October — RoomNights | C4: October — Pickup % | D4: December — RoomNights | E4: December — Pickup %
A5: 180 | B5: =SUMIFS(Pickup_Detail!$E$2:$E$265,Pickup_Detail!$B$2:$B$265,10,Pickup_Detail!$D$2:$D$265,">="&A5) -> 172 | C5: =B5/9300 -> 0.018494624 | D5: =SUMIFS(Pickup_Detail!$E$2:$E$265,Pickup_Detail!$B$2:$B$265,12,Pickup_Detail!$D$2:$D$265,">="&A5) -> 136 | E5: =D5/9300 -> 0.014623656
A6: 120 | B6: =SUMIFS(Pickup_Detail!$E$2:$E$265,Pickup_Detail!$B$2:$B$265,10,Pickup_Detail!$D$2:$D$265,">="&A6) -> 388 | C6: =B6/9300 -> 0.04172043 | D6: =SUMIFS(Pickup_Detail!$E$2:$E$265,Pickup_Detail!$B$2:$B$265,12,Pickup_Detail!$D$2:$D$265,">="&A6) -> 305 | E6: =D6/9300 -> 0.032795699
A7: 90 | B7: =SUMIFS(Pickup_Detail!$E$2:$E$265,Pickup_Detail!$B$2:$B$265,10,Pickup_Detail!$D$2:$D$265,">="&A7) -> 752 | C7: =B7/9300 -> 0.080860215 | D7: =SUMIFS(Pickup_Detail!$E$2:$E$265,Pickup_Detail!$B$2:$B$265,12,Pickup_Detail!$D$2:$D$265,">="&A7) -> 595 | E7: =D7/9300 -> 0.063978495
A8: 60 | B8: =SUMIFS(Pickup_Detail!$E$2:$E$265,Pickup_Detail!$B$2:$B$265,10,Pickup_Detail!$D$2:$D$265,">="&A8) -> 1177 | C8: =B8/9300 -> 0.12655914 | D8: =SUMIFS(Pickup_Detail!$E$2:$E$265,Pickup_Detail!$B$2:$B$265,12,Pickup_Detail!$D$2:$D$265,">="&A8) -> 936 | E8: =D8/9300 -> 0.10064516
A9: 45 | B9: =SUMIFS(Pickup_Detail!$E$2:$E$265,Pickup_Detail!$B$2:$B$265,10,Pickup_Detail!$D$2:$D$265,">="&A9) -> 1428 | C9: =B9/9300 -> 0.15354839 | D9: =SUMIFS(Pickup_Detail!$E$2:$E$265,Pickup_Detail!$B$2:$B$265,12,Pickup_Detail!$D$2:$D$265,">="&A9) -> 1135 | E9: =D9/9300 -> 0.12204301
A10: 30 | B10: =SUMIFS(Pickup_Detail!$E$2:$E$265,Pickup_Detail!$B$2:$B$265,10,Pickup_Detail!$D$2:$D$265,">="&A10) -> 1841 | C10: =B10/9300 -> 0.19795699 | D10: =SUMIFS(Pickup_Detail!$E$2:$E$265,Pickup_Detail!$B$2:$B$265,12,Pickup_Detail!$D$2:$D$265,">="&A10) -> 1461 | E10: =D10/9300 -> 0.15709677
A11: 21 | B11: =SUMIFS(Pickup_Detail!$E$2:$E$265,Pickup_Detail!$B$2:$B$265,10,Pickup_Detail!$D$2:$D$265,">="&A11) -> 2207 | C11: =B11/9300 -> 0.23731183 | D11: =SUMIFS(Pickup_Detail!$E$2:$E$265,Pickup_Detail!$B$2:$B$265,12,Pickup_Detail!$D$2:$D$265,">="&A11) -> 1748 | E11: =D11/9300 -> 0.18795699
A12: 14 | B12: =SUMIFS(Pickup_Detail!$E$2:$E$265,Pickup_Detail!$B$2:$B$265,10,Pickup_Detail!$D$2:$D$265,">="&A12) -> 2988 | C12: =B12/9300 -> 0.32129032 | D12: =SUMIFS(Pickup_Detail!$E$2:$E$265,Pickup_Detail!$B$2:$B$265,12,Pickup_Detail!$D$2:$D$265,">="&A12) -> 2363 | E12: =D12/9300 -> 0.25408602
A13: 7 | B13: =SUMIFS(Pickup_Detail!$E$2:$E$265,Pickup_Detail!$B$2:$B$265,10,Pickup_Detail!$D$2:$D$265,">="&A13) -> 3904 | C13: =B13/9300 -> 0.41978495 | D13: =SUMIFS(Pickup_Detail!$E$2:$E$265,Pickup_Detail!$B$2:$B$265,12,Pickup_Detail!$D$2:$D$265,">="&A13) -> 3073 | E13: =D13/9300 -> 0.33043011
A14: 3 | B14: =SUMIFS(Pickup_Detail!$E$2:$E$265,Pickup_Detail!$B$2:$B$265,10,Pickup_Detail!$D$2:$D$265,">="&A14) -> 4821 | C14: =B14/9300 -> 0.5183871 | D14: =SUMIFS(Pickup_Detail!$E$2:$E$265,Pickup_Detail!$B$2:$B$265,12,Pickup_Detail!$D$2:$D$265,">="&A14) -> 3792 | E14: =D14/9300 -> 0.40774194
A15: 0 | B15: =SUMIFS(Pickup_Detail!$E$2:$E$265,Pickup_Detail!$B$2:$B$265,10,Pickup_Detail!$D$2:$D$265,">="&A15) -> 5538 | C15: =B15/9300 -> 0.59548387 | D15: =SUMIFS(Pickup_Detail!$E$2:$E$265,Pickup_Detail!$B$2:$B$265,12,Pickup_Detail!$D$2:$D$265,">="&A15) -> 4351 | E15: =D15/9300 -> 0.46784946
A18: Reading this report
A19: At 30 days before arrival, December is running well behind October's pace at the same point — the gap that matters most, since it's still early enough to act on with a tactical push (see Recommendations).

Sheet Group_Displacement
A1: Group Business Displacement Analysis
A2: Evaluates each group request against the transient (non-group) demand it would displace on those dates, using the Demand_Pattern day-of-week averages. Yellow cells are the request inputs — edit to test other scenarios.
A4: Scenario | B4: Arrival Date | C4: Nights | D4: Rooms/Night Requested | E4: Proposed Group Rate | F4: Group Revenue | G4: Day of Week | H4: Expected Transient Occ % | I4: Expected Transient Demand (rooms) | J4: Rooms Left for Transient | K4: Displaced Rooms/Night | L4: Total Displaced RoomNights | M4: Transient ADR | N4: Displaced Revenue | O4: Net Revenue Impact | P4: Recommendation
A5: Spring Conference | B5: 2025-05-14 | C5: 3 | D5: 150 | E5: 85 | F5: =C5*D5*E5 -> 38250 | G5: =TEXT(B5,"dddd") -> Wednesday | H5: =INDEX(Demand_Pattern!$B$4:$B$10,MATCH(G5,Demand_Pattern!$A$4:$A$10,0)) -> 0.55106918 | I5: =ROUND(H5*300,0) -> 165 | J5: =300-D5 -> 150 | K5: =MAX(0,I5-J5) -> 15 | L5: =K5*C5 -> 45 | M5: =INDEX(Demand_Pattern!$C$4:$C$10,MATCH(G5,Demand_Pattern!$A$4:$A$10,0)) -> 107.41384 | N5: =L5*M5 -> 4833.623 | O5: =F5-N5 -> 33416.377 | P5: =IF(O5>0,"Accept","Negotiate Rate Up") -> Accept
A6: Summer Wedding Block | B6: 2025-07-19 | C6: 1 | D6: 60 | E6: 110 | F6: =C6*D6*E6 -> 6600 | G6: =TEXT(B6,"dddd") -> Saturday | H6: =INDEX(Demand_Pattern!$B$4:$B$10,MATCH(G6,Demand_Pattern!$A$4:$A$10,0)) -> 0.39967949 | I6: =ROUND(H6*300,0) -> 120 | J6: =300-D6 -> 240 | K6: =MAX(0,I6-J6) -> 0 | L6: =K6*C6 -> 0 | M6: =INDEX(Demand_Pattern!$C$4:$C$10,MATCH(G6,Demand_Pattern!$A$4:$A$10,0)) -> 98.434965 | N6: =L6*M6 -> 0 | O6: =F6-N6 -> 6600 | P6: =IF(O6>0,"Accept","Negotiate Rate Up") -> Accept
A7: Autumn Trade Show | B7: 2025-10-08 | C7: 4 | D7: 270 | E7: 50 | F7: =C7*D7*E7 -> 54000 | G7: =TEXT(B7,"dddd") -> Wednesday | H7: =INDEX(Demand_Pattern!$B$4:$B$10,MATCH(G7,Demand_Pattern!$A$4:$A$10,0)) -> 0.55106918 | I7: =ROUND(H7*300,0) -> 165 | J7: =300-D7 -> 30 | K7: =MAX(0,I7-J7) -> 135 | L7: =K7*C7 -> 540 | M7: =INDEX(Demand_Pattern!$C$4:$C$10,MATCH(G7,Demand_Pattern!$A$4:$A$10,0)) -> 107.41384 | N7: =L7*M7 -> 58003.476 | O7: =F7-N7 -> -4003.4761 | P7: =IF(O7>0,"Accept","Negotiate Rate Up") -> Negotiate Rate Up
A8: January Corp Offsite | B8: 2025-01-15 | C8: 2 | D8: 100 | E8: 70 | F8: =C8*D8*E8 -> 14000 | G8: =TEXT(B8,"dddd") -> Wednesday | H8: =INDEX(Demand_Pattern!$B$4:$B$10,MATCH(G8,Demand_Pattern!$A$4:$A$10,0)) -> 0.55106918 | I8: =ROUND(H8*300,0) -> 165 | J8: =300-D8 -> 200 | K8: =MAX(0,I8-J8) -> 0 | L8: =K8*C8 -> 0 | M8: =INDEX(Demand_Pattern!$C$4:$C$10,MATCH(G8,Demand_Pattern!$A$4:$A$10,0)) -> 107.41384 | N8: =L8*M8 -> 0 | O8: =F8-N8 -> 14000 | P8: =IF(O8>0,"Accept","Negotiate Rate Up") -> Accept
A9: Dec Holiday Party | B9: 2025-12-06 | C9: 1 | D9: 40 | E9: 75 | F9: =C9*D9*E9 -> 3000 | G9: =TEXT(B9,"dddd") -> Saturday | H9: =INDEX(Demand_Pattern!$B$4:$B$10,MATCH(G9,Demand_Pattern!$A$4:$A$10,0)) -> 0.39967949 | I9: =ROUND(H9*300,0) -> 120 | J9: =300-D9 -> 260 | K9: =MAX(0,I9-J9) -> 0 | L9: =K9*C9 -> 0 | M9: =INDEX(Demand_Pattern!$C$4:$C$10,MATCH(G9,Demand_Pattern!$A$4:$A$10,0)) -> 98.434965 | N9: =L9*M9 -> 0 | O9: =F9-N9 -> 3000 | P9: =IF(O9>0,"Accept","Negotiate Rate Up") -> Accept

Sheet Forecast
A1: Forward Forecast — Q1 2026
A2: Simple YoY-growth forecast off FY2025 actuals. Growth assumptions (yellow) are editable — a production forecast would weight recent Pickup_Report pace more heavily than a flat growth rate.
A4: Occupancy growth assumption (YoY) | C4: 0.02
A5: ADR growth assumption (YoY) | C5: 0.03
A7: Month | B7: Prior-Year Occ % | C7: Forecast Occ % | D7: Prior-Year ADR | E7: Forecast ADR | F7: Forecast RevPAR | G7: Forecast Room Revenue
A8: January 2026 | B8: =INDEX(KPI_Summary!$E$4:$E$15,MATCH("January",KPI_Summary!$A$4:$A$15,0)) -> 0.38258065 | C8: =B8*(1+$C$4) -> 0.39023226 | D8: =INDEX(KPI_Summary!$F$4:$F$15,MATCH("January",KPI_Summary!$A$4:$A$15,0)) -> 97.532122 | E8: =D8*(1+$C$5) -> 100.45809 | F8: =C8*E8 -> 39.201986 | G8: =F8*300*31 -> 364578.47
A9: February 2026 | B9: =INDEX(KPI_Summary!$E$4:$E$15,MATCH("February",KPI_Summary!$A$4:$A$15,0)) -> 0.4525 | C9: =B9*(1+$C$4) -> 0.46155 | D9: =INDEX(KPI_Summary!$F$4:$F$15,MATCH("February",KPI_Summary!$A$4:$A$15,0)) -> 101.0578 | E9: =D9*(1+$C$5) -> 104.08953 | F9: =C9*E9 -> 48.042522 | G9: =F9*300*28 -> 403557.19
A10: March 2026 | B10: =INDEX(KPI_Summary!$E$4:$E$15,MATCH("March",KPI_Summary!$A$4:$A$15,0)) -> 0.53301075 | C10: =B10*(1+$C$4) -> 0.54367097 | D10: =INDEX(KPI_Summary!$F$4:$F$15,MATCH("March",KPI_Summary!$A$4:$A$15,0)) -> 106.59449 | E10: =D10*(1+$C$5) -> 109.79233 | F10: =C10*E10 -> 59.6909 | G10: =F10*300*31 -> 555125.37

Sheet Dashboard
B2: Meridian City Hotel — Revenue Dashboard (FY2025, synthetic)
B4: Annual Occupancy | E4: Annual ADR | H4: Annual RevPAR | K4: RGI vs Comp Set
B5: =KPI_Summary!E16 -> 0.50989041 | E5: =KPI_Summary!F16 -> 105.75943 | H5: =KPI_Summary!G16 -> 53.925717 | K5: =CompSet!B14 -> 99.736845

Sheet Recommendations
B2: Findings & Pricing Recommendations
B3: Based on the FY2025 synthetic dataset. Figures match the linked KPI, Segment, CompSet, Pickup and Group_Displacement tabs.
B5: 1. Close the weekend occupancy gap
B6: Weekday occupancy averages ~55%, but Saturday and Sunday sit closer to 40% — a c.15-point gap driven by the corporate segment's near-total absence at weekends. Recommend a dedicated weekend leisure package (rate-inclusive extras: parking, breakfast, spa credit) marketed directly and via OTA to target this specific gap, rather than a blanket rate cut.
B8: 2. Manage OTA mix rather than eliminate it
B9: OTA carries the lowest ADR of the four segments (~£88 vs. a ~£105 hotel-wide average) and delivers a disproportionately larger share of room nights (20%) than revenue (17%). Recommend capping OTA allocation during high-demand weekday periods via rate parity and availability controls, while keeping it open as the primary weekend-fill channel identified in point 1.
B11: 3. Protect Corporate rate integrity
B12: Corporate is the highest-value segment — 46% of room nights but 51% of revenue, and the highest ADR of any segment (~£118). This is the segment most exposed to margin erosion from over-discounting during high-demand periods (Sept-Nov). Recommend a rate floor for negotiated corporate accounts during peak conference months.
B14: 4. December is pacing behind October at the same lead time — act now, not in December
B15: The Pickup_Report shows December running visibly behind October's pace at every checkpoint (e.g. 30 days out: October at ~20% of rooms on the books vs December at ~16%). Both are measured at the same lead time, so this is a genuine pace gap, not just December being a shorter look-back. With 30+ days still on the clock, recommend triggering a December tactical rate/package promotion now, while there's still enough lead time for it to move the outcome — waiting until December's occupancy has already printed low is too late to fix it.
B17: 5. Push back on the Autumn Trade Show group rate as quoted
B18: The Group_Displacement analysis flags one of five live group scenarios as value-destructive as quoted: the Autumn Trade Show wants 270 of 300 rooms for 4 nights at £50 — a c.55% discount to standard ADR during the single highest-demand week of the year. At that rate and block size, the group would displace an estimated 540 room-nights of transient business worth more than the group itself, for a net impact of roughly -£4,000. Recommend countering at a higher rate or a smaller room block rather than declining outright — the volume has real value, just not at the rate quoted. The other four group scenarios modelled are net-positive as-is and can be accepted.
... B24: The Forecast tab projects Q1 2026 RevPAR by applying flat YoY growth assumptions (2% occupancy, 3% ADR) to FY2025 actuals — useful for an early budget baseline, but it doesn't yet reflect actual pickup on the books. Recommend re-running the forecast against real January/February pace once it's available, using the same lead-time logic as the Pickup_Report, rather than relying on the YoY assumption past the point where real booking data exists.
